hackhttp2/__init__.py
hackhttp2/hackhttp.py
hackhttp2/utils/__init__.py
hackhttp2/utils/utils.py
hackhttp2-0.0.45.dist-info/METADATA
hackhttp2-0.0.45.dist-info/WHEEL
hackhttp2-0.0.45.dist-info/top_level.txt
hackhttp2-0.0.45.dist-info/RECORD
