Metadata-Version: 2.1
Name: hackhttp2
Version: 0.0.45
Summary: A small example package
Home-page: https://www.baidu.com
Author: ybw
Author-email: 2756456886@qq.com
License: UNKNOWN
Platform: UNKNOWN
Requires-Python: >=3.0
Requires-Dist: requests-toolbelt
Requires-Dist: netifaces
Requires-Dist: httpx
